{
  "version": "1",
  "cognitoConfig": {
    "identityPoolName": "authbarcodebattler_identitypool_1b91ce67",
    "allowUnauthenticatedIdentities": false,
    "resourceNameTruncated": "authba1b91ce67",
    "userPoolName": "authbarcodebattler_userpool_1b91ce67",
    "autoVerifiedAttributes": [
      "email"
    ],
    "mfaConfiguration": "OFF",
    "mfaTypes": [
      "SMS Text Message"
    ],
    "smsAuthenticationMessage": "Your authentication code is {####}",
    "smsVerificationMessage": "Your verification code is {####}",
    "emailVerificationSubject": "Your verification code",
    "emailVerificationMessage": "Your verification code is {####}",
    "defaultPasswordPolicy": false,
    "passwordPolicyMinLength": 8,
    "passwordPolicyCharacters": [],
    "requiredAttributes": [
      "email"
    ],
    "aliasAttributes": [],
    "userpoolClientGenerateSecret": false,
    "userpoolClientRefreshTokenValidity": 30,
    "userpoolClientWriteAttributes": [
      "email"
    ],
    "userpoolClientReadAttributes": [
      "email"
    ],
    "userpoolClientLambdaRole": "authba1b91ce67_userpoolclient_lambda_role",
    "userpoolClientSetAttributes": false,
    "authSelections": "identityPoolAndUserPool",
    "resourceName": "authbarcodebattler",
    "sharedId": "1b91ce67",
    "serviceName": "Cognito",
    "useDefault": "manual"
  }
}